Metadata-Version: 2.4
Name: pgradd
Version: 2.9.13
Summary: Python package implements the Group Additivity (GA) method for estimating thermodynamic properties
Home-page: https://github.com/VlachosGroup/PythonGroupAdditivity
Author: Vlachos Research Group
Author-email: vlachos@udel.edu
Classifier: Programming Language :: Python :: 3
Classifier: License :: OSI Approved :: MIT License
Classifier: Operating System :: OS Independent
Classifier: Intended Audience :: Science/Research
Classifier: Topic :: Scientific/Engineering :: Chemistry
License-File: LICENSE.md
Requires-Dist: pmutt>=1.3.2
Requires-Dist: scipy>=1.7.0
Requires-Dist: numpy>=1.21.0
Requires-Dist: IPython>=7.31.0
Requires-Dist: PyYAML>=6.0
Requires-Dist: rdkit>=2023.3.2
Dynamic: author
Dynamic: author-email
Dynamic: classifier
Dynamic: description
Dynamic: description-content-type
Dynamic: home-page
Dynamic: license-file
Dynamic: requires-dist
Dynamic: summary
